excel_management/__init__.py
excel_management/excel_management.py
RR_Excel_Management-0.1.2.dist-info/LICENSE
RR_Excel_Management-0.1.2.dist-info/METADATA
RR_Excel_Management-0.1.2.dist-info/WHEEL
RR_Excel_Management-0.1.2.dist-info/top_level.txt
RR_Excel_Management-0.1.2.dist-info/RECORD
