Metadata-Version: 2.1
Name: RR-Excel-Management
Version: 0.1.2
Summary: Frequent excel and dataframe operations library.
Author: Ronak Rathore
Author-email: ronak.rathore05@gmail.com
License: GNU GENERAL PUBLIC LICENSE
Classifier: Intended Audience :: Developers
Classifier: Programming Language :: Python
Classifier: Programming Language :: Python :: 3
Classifier: Programming Language :: Python :: 3.6
Classifier: Programming Language :: Python :: 3.7
Classifier: Programming Language :: Python :: 3.8
Classifier: Programming Language :: Python :: 3.9
Classifier: Operating System :: OS Independent
License-File: LICENSE
Requires-Dist: pandas
Requires-Dist: RR-Date-Management
Requires-Dist: openpyxl
Requires-Dist: pathlib
